dataprofilerkit/__init__.py
dataprofilerkit/profiler.py
dataprofilerkit/utils.py
data_profiler_kit-0.1.2.dist-info/LICENSE
data_profiler_kit-0.1.2.dist-info/METADATA
data_profiler_kit-0.1.2.dist-info/WHEEL
data_profiler_kit-0.1.2.dist-info/top_level.txt
data_profiler_kit-0.1.2.dist-info/RECORD
