Metadata-Version: 2.1
Name: data-profiler-kit
Version: 0.1.2
Summary: A library to provide quick and insightful data profiling for pandas DataFrames
Author-email: Najm Eddine Charaf <oldcharaf@gmail.com>
License: MIT License
Project-URL: Homepage, https://github.com/cnajmeddine/data-profiler
Keywords: data,profiling,pandas,analytics
Classifier: Programming Language :: Python :: 3
Classifier: License :: OSI Approved :: MIT License
Classifier: Operating System :: OS Independent
Requires-Python: >=3.7
License-File: LICENSE
Requires-Dist: pandas>=1.0.0
Requires-Dist: numpy>=1.18.0
